pynimate/__init__.py
pynimate/bar.py
pynimate/barhplot.py
pynimate/baseplot.py
pynimate/canvas.py
pynimate/datafier.py
pynimate/lineplot.py
pynimate/utils.py
pynimate-1.3.0.dist-info/LICENSE
pynimate-1.3.0.dist-info/METADATA
pynimate-1.3.0.dist-info/WHEEL
pynimate-1.3.0.dist-info/top_level.txt
pynimate-1.3.0.dist-info/RECORD
