Metadata-Version: 2.1
Name: pynimate
Version: 1.3.0
Summary: Python package for statistical data animations
Author-email: julkar9 <julkar9dev@gmail.com>
License: MIT License (MIT)
Project-URL: Homepage, https://github.com/julkaar9/pynimate
Project-URL: Documentation, https://julkaar9.github.io/pynimate/
Keywords: animations,framework,data,plots
Classifier: License :: OSI Approved :: MIT License
Classifier: Programming Language :: Python
Classifier: Programming Language :: Python :: 3
Classifier: Programming Language :: Python :: 3.9
Classifier: Programming Language :: Python :: 3.10
Classifier: Operating System :: OS Independent
Classifier: Topic :: Software Development :: Libraries :: Application Frameworks
Classifier: Topic :: Software Development :: Libraries :: Python Modules
Requires-Python: >=3.9
License-File: LICENSE
Requires-Dist: numpy
Requires-Dist: pandas
Requires-Dist: matplotlib
Requires-Dist: seaborn
Provides-Extra: dev
Requires-Dist: black ; extra == 'dev'
Requires-Dist: isort ; extra == 'dev'
Requires-Dist: mkdocs-material ; extra == 'dev'
Requires-Dist: pip-tools ; extra == 'dev'
Requires-Dist: pytest ; extra == 'dev'
Requires-Dist: mkdocstrings[python] ; extra == 'dev'
